autora/runner/firebase_prolific/__init__.py
autora_runner_firebase_prolific-0.1.0.dist-info/METADATA
autora_runner_firebase_prolific-0.1.0.dist-info/WHEEL
autora_runner_firebase_prolific-0.1.0.dist-info/top_level.txt
autora_runner_firebase_prolific-0.1.0.dist-info/RECORD
