Metadata-Version: 2.1
Name: autora-runner-firebase-prolific
Version: 0.1.0
Summary: AutoRA Firebase Prolific Runner provides runners to run experiments with prolific and firebase
Author-email: Younes Strittmatter <younes_strittmatter@brown.edu>
License: MIT License
Project-URL: homepage, http://www.empiricalresearch.ai
Project-URL: repository, https://github.com/AutoResearch/autora-runner-firebase-prolific
Project-URL: documentation, https://autoresearch.github.io/autora/
Requires-Python: <4,>=3.8
Requires-Dist: autora-core
Requires-Dist: autora-runner-recruitment-manager-prolific
Requires-Dist: autora-runner-experimentation-manager-firebase
Provides-Extra: dev
Requires-Dist: autora-core[dev] ; extra == 'dev'
